multisort/.python-version
multisort/__init__.py
multisort/multisort.py
multisort-0.1.5.dist-info/LICENSE
multisort-0.1.5.dist-info/METADATA
multisort-0.1.5.dist-info/WHEEL
multisort-0.1.5.dist-info/RECORD
